puppettable/__init__.py
puppettable/implementations/__init__.py
puppettable/implementations/azure/__init__.py
puppettable/implementations/azure/azure_table_service.py
puppettable/implementations/azure/azure_table_stub.py
puppettable/implementations/azure/azure_table_stub_dictionary.py
puppettable/implementations/azure/azure_table_stub_indexed.py
puppettable/implementations/azure/progress/__init__.py
puppettable/implementations/azure/progress/update_progress.py
puppettable/interface/__init__.py
puppettable/interface/table_service.py
puppettable/interface/table_stub.py
puppettable/utils/__init__.py
puppettable/utils/azure_decorators.py
puppettable/utils/azure_parsers.py
puppettable/utils/progress.py
tests/__init__.py
tests/azure_test_table_dictionary.py
tests/azure_test_table_indexed.py
puppettable-0.0.1.dist-info/METADATA
puppettable-0.0.1.dist-info/WHEEL
puppettable-0.0.1.dist-info/top_level.txt
puppettable-0.0.1.dist-info/RECORD
