Metadata-Version: 2.1
Name: puppettable
Version: 0.0.1
Summary: A highly scalable table backed up by Azure Table Storage, with improved functionality.
Home-page: http://github.com/ipazc/puppettable
Author: Iván de Paz Centeno
Author-email: ipazc@unileon.es
License: UNKNOWN
Keywords: puppettable azure table storage python
Platform: UNKNOWN
Classifier: Environment :: Console
Classifier: Intended Audience :: Developers
Classifier: Intended Audience :: Education
Classifier: Intended Audience :: Science/Research
Classifier: Natural Language :: English
Classifier: Programming Language :: Python :: 3.6
Classifier: Programming Language :: Python :: 3.7
Requires-Dist: pandas (>=1.0.5)
Requires-Dist: azure-cosmosdb-table (==1.0.6)
Requires-Dist: nose (>=1.3.7)
Requires-Dist: pyarrow (>=0.17.1)
Requires-Dist: tqdm (>=4.48.0)
